gema_utils/__init__.py
gema_utils/_nbdev.py
gema_utils/nifti_utils.py
gema_utils-0.0.1.dist-info/LICENSE
gema_utils-0.0.1.dist-info/METADATA
gema_utils-0.0.1.dist-info/WHEEL
gema_utils-0.0.1.dist-info/entry_points.txt
gema_utils-0.0.1.dist-info/top_level.txt
gema_utils-0.0.1.dist-info/RECORD
