Metadata-Version: 2.1
Name: gema-utils
Version: 0.0.1
Summary: A python suite to complement CLARA (NVIDIA's healthcare application)
Home-page: https://github.com/pfdamasceno/gema_utils
Author: Pablo F. Damasceno
Author-email: pablodamasceno@gmail.com
License: Apache Software License 2.0
Keywords: nifti,neuroimaging
Platform: UNKNOWN
Classifier: Development Status :: 3 - Alpha
Classifier: Intended Audience :: Developers
Classifier: License :: OSI Approved :: Apache Software License
Classifier: Natural Language :: English
Classifier: Programming Language :: Python :: 3.6
Classifier: Programming Language :: Python :: 3.7
Classifier: Programming Language :: Python :: 3.8
Requires-Python: >=3.6
